graphs_colinr135/__init__.py
graphs_colinr135/heapq.py
graphs_colinr135/sp.py
graphs_colinr135-0.0.2.dist-info/METADATA
graphs_colinr135-0.0.2.dist-info/WHEEL
graphs_colinr135-0.0.2.dist-info/RECORD
