Metadata-Version: 2.4
Name: graphs_colinr135
Version: 0.0.2
Summary: A package for the Dijkstra algorithm
Project-URL: Homepage, https://github.com/ColinR135/graph_colinr135.git
Author-email: Colin Reed <creed40@msudenver.edu>
Classifier: License :: OSI Approved :: MIT License
Classifier: Operating System :: OS Independent
Classifier: Programming Language :: Python :: 3
Requires-Python: >=3.7
